Workbook

Sheet Instructions
A1: Loan Restructuring Calculator — How to Use
A3: Purpose | B3: Encodes an existing loan's details, lets you enter the borrower's last payment date and days-past-due (DPD), and automatically computes the restructured loan — with the basis for every figure shown.
A5: Color legend
A6: Blue bold text on yellow fill | B6: Means: input cell. This is the ONLY thing you should type into.
A7: Black text | B7: Means: formula. Do not overwrite — it recalculates automatically.
A8: Green text | B8: Means: a value linked in from another sheet.
A10: Sheet order
A11: 1. Original Loan Setup | B11: Encode the existing loan's terms (principal, rate, term, fees) exactly as shown on its Promissory Note.
A12: 2. Original Amortization Schedule | B12: Auto-generated from Sheet 1 — mirrors the bank's amortization schedule format.
A13: 3. Restructuring Workup | B13: Enter the Last Payment Date and DPD here. Everything else on this sheet — outstanding principal, accrued interest, penalty, and the new restructured principal — is calculated, with its basis stated next to each figure. Policy: DPD > 90 days -> restructured principal = Outstanding Principal only. DPD <= 90 days -> restructured principal = Outstanding Principal + Accrued Interest. (Penalty capitalization is a separate manual Yes/No toggle.)
A14: 4. Restructured Amortization Schedule | B14: Auto-generated new schedule for the restructured loan, same mechanics as Sheet 2.
A15: 5. Summary | B15: Side-by-side comparison of the original vs. restructured loan for quick reference.
A17: Sample scenario | B17: This workbook ships pre-filled with an illustrative unsecured cash loan scenario (₱20,000 principal, 95% APR, 12 installments, restructured into a 47.5% APR, 16-installment loan) so you can see how the mechanics work end-to-end. No client or borrower information is stored in this file. Overwrite the yellow cells on Sheets 1 and 3 with a real loan's terms to use the calculator.

Sheet 1. Original Loan Setup
A1: Original Loan — Encoded Details
B2: Source: Tonik Digital Bank Promissory Note. Yellow cells are inputs — replace with a new borrower's terms to reuse this workbook.
B4: LOAN IDENTIFICATION
B5: Loan Reference / ID (optional, internal use) | C5: e.g. LN-000001
B7: ORIGINAL LOAN TERMS (per Promissory Note)
B8: Principal Amount (PHP) | C8: 20000
B9: Date Granted | C9: 45991
B10: Annual Interest Rate (APR) | C10: 0.95
B11: Monthly Interest Rate | C11: =C10/12 -> 0.079166667
B12: Number of Installments | C12: 12
B13: First Monthly Due Date | C13: 46024
B14: Processing Fee (PHP) | C14: 500
B15: Documentary Stamps Tax (PHP) | C15: 150
B16: Net Proceeds of Loan (PHP) | C16: =C8-C14-C15 -> 19350
B17: Value-Added Services (VAS) Fee % | C17: 0.0911
B18: VAS fee = this % applied to each installment's (principal + interest).
B19: Late Payment Fee per missed installment (PHP) | C19: 500
B21: COMPUTED SUMMARY (for reference)
B22: Fixed Monthly Installment (Principal+Interest) | C22: =-PMT(C11,C12,C8) -> 2642.4529
B23: Maturity Date | C23: =EDATE(C13,C12-1) -> 46358

Sheet 2. Original Amort Schedule
A1: Original Loan — Amortization Schedule
A2: Auto-generated from Sheet 1. Installment = fixed annuity payment at the Monthly Rate (Principal+Interest constant every period, via the PMT function). Interest = Beginning Balance x (Annual Rate/365) x actual days in the billing cycle (28/30/31, per the calendar month ending on each installment date) — this reproduces the source Promissory Note's schedule to the peso for installments 1-11. Principal = Installment - Interest, except the FINAL installment, which pays off the remaining balance exactly; banks typically true up the final installment's interest so total interest matches the amount disclosed at origination, so this model's last-row interest can differ slightly from the bank's own statement (immaterial to the outstanding-principal figures the restructuring calculation relies on). VAS Fee = 9.11% of (Principal+Interest).
A4: No. | B4: Installment Date | C4: Beginning Balance | D4: Principal | E4: Interest | F4: VAS Fee | G4: Total Payment | H4: Ending Balance
A5: =IF(1<='1. Original Loan Setup'!$C$12,1,"") -> 1 | B5: =IF(1<='1. Original Loan Setup'!$C$12,EDATE('1. Original Loan Setup'!$C$13,1-1),"") -> 46024 | C5: =IF(1<='1. Original Loan Setup'!$C$12,'1. Original Loan Setup'!$C$8,"") -> 20000 | D5: =IF(1<'1. Original Loan Setup'!$C$12,'1. Original Loan Setup'!$C$22-E5,IF(1='1. Original Loan Setup'!$C$12,C5,"")) -> 1028.7543 | E5: =IF(1<='1. Original Loan Setup'!$C$12,C5*'1. Original Loan Setup'!$C$10/365*(B5-EDATE(B5,-1)),"") -> 1613.6986 | F5: =IF(1<='1. Original Loan Setup'!$C$12,(D5+E5)*'1. Original Loan Setup'!$C$17,"") -> 240.72746 | G5: =IF(1<='1. Original Loan Setup'!$C$12,D5+E5+F5,"") -> 2883.1803 | H5: =IF(1<='1. Original Loan Setup'!$C$12,C5-D5,"") -> 18971.246
A6: =IF(2<='1. Original Loan Setup'!$C$12,2,"") -> 2 | B6: =IF(2<='1. Original Loan Setup'!$C$12,EDATE('1. Original Loan Setup'!$C$13,2-1),"") -> 46055 | C6: =IF(2<='1. Original Loan Setup'!$C$12,H5,"") -> 18971.246 | D6: =IF(2<'1. Original Loan Setup'!$C$12,'1. Original Loan Setup'!$C$22-E6,IF(2='1. Original Loan Setup'!$C$12,C6,"")) -> 1111.7592 | E6: =IF(2<='1. Original Loan Setup'!$C$12,C6*'1. Original Loan Setup'!$C$10/365*(B6-EDATE(B6,-1)),"") -> 1530.6937 | F6: =IF(2<='1. Original Loan Setup'!$C$12,(D6+E6)*'1. Original Loan Setup'!$C$17,"") -> 240.72746 | G6: =IF(2<='1. Original Loan Setup'!$C$12,D6+E6+F6,"") -> 2883.1803 | H6: =IF(2<='1. Original Loan Setup'!$C$12,C6-D6,"") -> 17859.487
A7: =IF(3<='1. Original Loan Setup'!$C$12,3,"") -> 3 | B7: =IF(3<='1. Original Loan Setup'!$C$12,EDATE('1. Original Loan Setup'!$C$13,3-1),"") -> 46083 | C7: =IF(3<='1. Original Loan Setup'!$C$12,H6,"") -> 17859.487 | D7: =IF(3<'1. Original Loan Setup'!$C$12,'1. Original Loan Setup'!$C$22-E7,IF(3='1. Original Loan Setup'!$C$12,C7,"")) -> 1340.9122 | E7: =IF(3<='1. Original Loan Setup'!$C$12,C7*'1. Original Loan Setup'!$C$10/365*(B7-EDATE(B7,-1)),"") -> 1301.5407 | F7: =IF(3<='1. Original Loan Setup'!$C$12,(D7+E7)*'1. Original Loan Setup'!$C$17,"") -> 240.72746 | G7: =IF(3<='1. Original Loan Setup'!$C$12,D7+E7+F7,"") -> 2883.1803 | H7: =IF(3<='1. Original Loan Setup'!$C$12,C7-D7,"") -> 16518.574
A8: =IF(4<='1. Original Loan Setup'!$C$12,4,"") -> 4 | B8: =IF(4<='1. Original Loan Setup'!$C$12,EDATE('1. Original Loan Setup'!$C$13,4-1),"") -> 46114 | C8: =IF(4<='1. Original Loan Setup'!$C$12,H7,"") -> 16518.574 | D8: =IF(4<'1. Original Loan Setup'!$C$12,'1. Original Loan Setup'!$C$22-E8,IF(4='1. Original Loan Setup'!$C$12,C8,"")) -> 1309.6528 | E8: =IF(4<='1. Original Loan Setup'!$C$12,C8*'1. Original Loan Setup'!$C$10/365*(B8-EDATE(B8,-1)),"") -> 1332.8 | F8: =IF(4<='1. Original Loan Setup'!$C$12,(D8+E8)*'1. Original Loan Setup'!$C$17,"") -> 240.72746 | G8: =IF(4<='1. Original Loan Setup'!$C$12,D8+E8+F8,"") -> 2883.1803 | H8: =IF(4<='1. Original Loan Setup'!$C$12,C8-D8,"") -> 15208.921
A9: =IF(5<='1. Original Loan Setup'!$C$12,5,"") -> 5 | B9: =IF(5<='1. Original Loan Setup'!$C$12,EDATE('1. Original Loan Setup'!$C$13,5-1),"") -> 46144 | C9: =IF(5<='1. Original Loan Setup'!$C$12,H8,"") -> 15208.921 | D9: =IF(5<'1. Original Loan Setup'!$C$12,'1. Original Loan Setup'!$C$22-E9,IF(5='1. Original Loan Setup'!$C$12,C9,"")) -> 1454.907 | E9: =IF(5<='1. Original Loan Setup'!$C$12,C9*'1. Original Loan Setup'!$C$10/365*(B9-EDATE(B9,-1)),"") -> 1187.5459 | F9: =IF(5<='1. Original Loan Setup'!$C$12,(D9+E9)*'1. Original Loan Setup'!$C$17,"") -> 240.72746 | G9: =IF(5<='1. Original Loan Setup'!$C$12,D9+E9+F9,"") -> 2883.1803 | H9: =IF(5<='1. Original Loan Setup'!$C$12,C9-D9,"") -> 13754.015
A10: =IF(6<='1. Original Loan Setup'!$C$12,6,"") -> 6 | B10: =IF(6<='1. Original Loan Setup'!$C$12,EDATE('1. Original Loan Setup'!$C$13,6-1),"") -> 46175 | C10: =IF(6<='1. Original Loan Setup'!$C$12,H9,"") -> 13754.015 | D10: =IF(6<'1. Original Loan Setup'!$C$12,'1. Original Loan Setup'!$C$22-E10,IF(6='1. Original Loan Setup'!$C$12,C10,"")) -> 1532.7112 | E10: =IF(6<='1. Original Loan Setup'!$C$12,C10*'1. Original Loan Setup'!$C$10/365*(B10-EDATE(B10,-1)),"") -> 1109.7417 | F10: =IF(6<='1. Original Loan Setup'!$C$12,(D10+E10)*'1. Original Loan Setup'!$C$17,"") -> 240.72746 | G10: =IF(6<='1. Original Loan Setup'!$C$12,D10+E10+F10,"") -> 2883.1803 | H10: =IF(6<='1. Original Loan Setup'!$C$12,C10-D10,"") -> 12221.303
A11: =IF(7<='1. Original Loan Setup'!$C$12,7,"") -> 7 | B11: =IF(7<='1. Original Loan Setup'!$C$12,EDATE('1. Original Loan Setup'!$C$13,7-1),"") -> 46205 | C11: =IF(7<='1. Original Loan Setup'!$C$12,H10,"") -> 12221.303 | D11: =IF(7<'1. Original Loan Setup'!$C$12,'1. Original Loan Setup'!$C$22-E11,IF(7='1. Original Loan Setup'!$C$12,C11,"")) -> 1688.1867 | E11: =IF(7<='1. Original Loan Setup'!$C$12,C11*'1. Original Loan Setup'!$C$10/365*(B11-EDATE(B11,-1)),"") -> 954.26615 | F11: =IF(7<='1. Original Loan Setup'!$C$12,(D11+E11)*'1. Original Loan Setup'!$C$17,"") -> 240.72746 | G11: =IF(7<='1. Original Loan Setup'!$C$12,D11+E11+F11,"") -> 2883.1803 | H11: =IF(7<='1. Original Loan Setup'!$C$12,C11-D11,"") -> 10533.117
A12: =IF(8<='1. Original Loan Setup'!$C$12,8,"") -> 8 | B12: =IF(8<='1. Original Loan Setup'!$C$12,EDATE('1. Original Loan Setup'!$C$13,8-1),"") -> 46236 | C12: =IF(8<='1. Original Loan Setup'!$C$12,H11,"") -> 10533.117 | D12: =IF(8<'1. Original Loan Setup'!$C$12,'1. Original Loan Setup'!$C$22-E12,IF(8='1. Original Loan Setup'!$C$12,C12,"")) -> 1792.5891 | E12: =IF(8<='1. Original Loan Setup'!$C$12,C12*'1. Original Loan Setup'!$C$10/365*(B12-EDATE(B12,-1)),"") -> 849.86379 | F12: =IF(8<='1. Original Loan Setup'!$C$12,(D12+E12)*'1. Original Loan Setup'!$C$17,"") -> 240.72746 | G12: =IF(8<='1. Original Loan Setup'!$C$12,D12+E12+F12,"") -> 2883.1803 | H12: =IF(8<='1. Original Loan Setup'!$C$12,C12-D12,"") -> 8740.5275
A13: =IF(9<='1. Original Loan Setup'!$C$12,9,"") -> 9 | B13: =IF(9<='1. Original Loan Setup'!$C$12,EDATE('1. Original Loan Setup'!$C$13,9-1),"") -> 46267 | C13: =IF(9<='1. Original Loan Setup'!$C$12,H12,"") -> 8740.5275 | D13: =IF(9<'1. Original Loan Setup'!$C$12,'1. Original Loan Setup'!$C$22-E13,IF(9='1. Original Loan Setup'!$C$12,C13,"")) -> 1937.224 | E13: =IF(9<='1. Original Loan Setup'!$C$12,C13*'1. Original Loan Setup'!$C$10/365*(B13-EDATE(B13,-1)),"") -> 705.22887 | F13: =IF(9<='1. Original Loan Setup'!$C$12,(D13+E13)*'1. Original Loan Setup'!$C$17,"") -> 240.72746 | G13: =IF(9<='1. Original Loan Setup'!$C$12,D13+E13+F13,"") -> 2883.1803 | H13: =IF(9<='1. Original Loan Setup'!$C$12,C13-D13,"") -> 6803.3035
A14: =IF(10<='1. Original Loan Setup'!$C$12,10,"") -> 10 | B14: =IF(10<='1. Original Loan Setup'!$C$12,EDATE('1. Original Loan Setup'!$C$13,10-1),"") -> 46297 | C14: =IF(10<='1. Original Loan Setup'!$C$12,H13,"") -> 6803.3035 | D14: =IF(10<'1. Original Loan Setup'!$C$12,'1. Original Loan Setup'!$C$22-E14,IF(10='1. Original Loan Setup'!$C$12,C14,"")) -> 2111.236 | E14: =IF(10<='1. Original Loan Setup'!$C$12,C14*'1. Original Loan Setup'!$C$10/365*(B14-EDATE(B14,-1)),"") -> 531.21685 | F14: =IF(10<='1. Original Loan Setup'!$C$12,(D14+E14)*'1. Original Loan Setup'!$C$17,"") -> 240.72746 | G14: =IF(10<='1. Original Loan Setup'!$C$12,D14+E14+F14,"") -> 2883.1803 | H14: =IF(10<='1. Original Loan Setup'!$C$12,C14-D14,"") -> 4692.0675
A15: =IF(11<='1. Original Loan Setup'!$C$12,11,"") -> 11 | B15: =IF(11<='1. Original Loan Setup'!$C$12,EDATE('1. Original Loan Setup'!$C$13,11-1),"") -> 46328 | C15: =IF(11<='1. Original Loan Setup'!$C$12,H14,"") -> 4692.0675 | D15: =IF(11<'1. Original Loan Setup'!$C$12,'1. Original Loan Setup'!$C$22-E15,IF(11='1. Original Loan Setup'!$C$12,C15,"")) -> 2263.8737 | E15: =IF(11<='1. Original Loan Setup'!$C$12,C15*'1. Original Loan Setup'!$C$10/365*(B15-EDATE(B15,-1)),"") -> 378.57914 | F15: =IF(11<='1. Original Loan Setup'!$C$12,(D15+E15)*'1. Original Loan Setup'!$C$17,"") -> 240.72746 | G15: =IF(11<='1. Original Loan Setup'!$C$12,D15+E15+F15,"") -> 2883.1803 | H15: =IF(11<='1. Original Loan Setup'!$C$12,C15-D15,"") -> 2428.1938
A16: =IF(12<='1. Original Loan Setup'!$C$12,12,"") -> 12 | B16: =IF(12<='1. Original Loan Setup'!$C$12,EDATE('1. Original Loan Setup'!$C$13,12-1),"") -> 46358 | C16: =IF(12<='1. Original Loan Setup'!$C$12,H15,"") -> 2428.1938 | D16: =IF(12<'1. Original Loan Setup'!$C$12,'1. Original Loan Setup'!$C$22-E16,IF(12='1. Original Loan Setup'!$C$12,C16,"")) -> 2428.1938 | E16: =IF(12<='1. Original Loan Setup'!$C$12,C16*'1. Original Loan Setup'!$C$10/365*(B16-EDATE(B16,-1)),"") -> 189.59869 | F16: =IF(12<='1. Original Loan Setup'!$C$12,(D16+E16)*'1. Original Loan Setup'!$C$17,"") -> 238.48089 | G16: =IF(12<='1. Original Loan Setup'!$C$12,D16+E16+F16,"") -> 2856.2733 | H16: =IF(12<='1. Original Loan Setup'!$C$12,C16-D16,"") -> 0
A17: =IF(13<='1. Original Loan Setup'!$C$12,13,"") | B17: =IF(13<='1. Original Loan Setup'!$C$12,EDATE('1. Original Loan Setup'!$C$13,13-1),"") | C17: =IF(13<='1. Original Loan Setup'!$C$12,H16,"") | D17: =IF(13<'1. Original Loan Setup'!$C$12,'1. Original Loan Setup'!$C$22-E17,IF(13='1. Original Loan Setup'!$C$12,C17,"")) | E17: =IF(13<='1. Original Loan Setup'!$C$12,C17*'1. Original Loan Setup'!$C$10/365*(B17-EDATE(B17,-1)),"") | F17: =IF(13<='1. Original Loan Setup'!$C$12,(D17+E17)*'1. Original Loan Setup'!$C$17,"") | G17: =IF(13<='1. Original Loan Setup'!$C$12,D17+E17+F17,"") | H17: =IF(13<='1. Original Loan Setup'!$C$12,C17-D17,"")
A18: =IF(14<='1. Original Loan Setup'!$C$12,14,"") | B18: =IF(14<='1. Original Loan Setup'!$C$12,EDATE('1. Original Loan Setup'!$C$13,14-1),"") | C18: =IF(14<='1. Original Loan Setup'!$C$12,H17,"") | D18: =IF(14<'1. Original Loan Setup'!$C$12,'1. Original Loan Setup'!$C$22-E18,IF(14='1. Original Loan Setup'!$C$12,C18,"")) | E18: =IF(14<='1. Original Loan Setup'!$C$12,C18*'1. Original Loan Setup'!$C$10/365*(B18-EDATE(B18,-1)),"") | F18: =IF(14<='1. Original Loan Setup'!$C$12,(D18+E18)*'1. Original Loan Setup'!$C$17,"") | G18: =IF(14<='1. Original Loan Setup'!$C$12,D18+E18+F18,"") | H18: =IF(14<='1. Original Loan Setup'!$C$12,C18-D18,"")
A19: =IF(15<='1. Original Loan Setup'!$C$12,15,"") | B19: =IF(15<='1. Original Loan Setup'!$C$12,EDATE('1. Original Loan Setup'!$C$13,15-1),"") | C19: =IF(15<='1. Original Loan Setup'!$C$12,H18,"") | D19: =IF(15<'1. Original Loan Setup'!$C$12,'1. Original Loan Setup'!$C$22-E19,IF(15='1. Original Loan Setup'!$C$12,C19,"")) | E19: =IF(15<='1. Original Loan Setup'!$C$12,C19*'1. Original Loan Setup'!$C$10/365*(B19-EDATE(B19,-1)),"") | F19: =IF(15<='1. Original Loan Setup'!$C$12,(D19+E19)*'1. Original Loan Setup'!$C$17,"") | G19: =IF(15<='1. Original Loan Setup'!$C$12,D19+E19+F19,"") | H19: =IF(15<='1. Original Loan Setup'!$C$12,C19-D19,"")
A20: =IF(16<='1. Original Loan Setup'!$C$12,16,"") | B20: =IF(16<='1. Original Loan Setup'!$C$12,EDATE('1. Original Loan Setup'!$C$13,16-1),"") | C20: =IF(16<='1. Original Loan Setup'!$C$12,H19,"") | D20: =IF(16<'1. Original Loan Setup'!$C$12,'1. Original Loan Setup'!$C$22-E20,IF(16='1. Original Loan Setup'!$C$12,C20,"")) | E20: =IF(16<='1. Original Loan Setup'!$C$12,C20*'1. Original Loan Setup'!$C$10/365*(B20-EDATE(B20,-1)),"") | F20: =IF(16<='1. Original Loan Setup'!$C$12,(D20+E20)*'1. Original Loan Setup'!$C$17,"") | G20: =IF(16<='1. Original Loan Setup'!$C$12,D20+E20+F20,"") | H20: =IF(16<='1. Original Loan Setup'!$C$12,C20-D20,"")
A21: =IF(17<='1. Original Loan Setup'!$C$12,17,"") | B21: =IF(17<='1. Original Loan Setup'!$C$12,EDATE('1. Original Loan Setup'!$C$13,17-1),"") | C21: =IF(17<='1. Original Loan Setup'!$C$12,H20,"") | D21: =IF(17<'1. Original Loan Setup'!$C$12,'1. Original Loan Setup'!$C$22-E21,IF(17='1. Original Loan Setup'!$C$12,C21,"")) | E21: =IF(17<='1. Original Loan Setup'!$C$12,C21*'1. Original Loan Setup'!$C$10/365*(B21-EDATE(B21,-1)),"") | F21: =IF(17<='1. Original Loan Setup'!$C$12,(D21+E21)*'1. Original Loan Setup'!$C$17,"") | G21: =IF(17<='1. Original Loan Setup'!$C$12,D21+E21+F21,"") | H21: =IF(17<='1. Original Loan Setup'!$C$12,C21-D21,"")
A22: =IF(18<='1. Original Loan Setup'!$C$12,18,"") | B22: =IF(18<='1. Original Loan Setup'!$C$12,EDATE('1. Original Loan Setup'!$C$13,18-1),"") | C22: =IF(18<='1. Original Loan Setup'!$C$12,H21,"") | D22: =IF(18<'1. Original Loan Setup'!$C$12,'1. Original Loan Setup'!$C$22-E22,IF(18='1. Original Loan Setup'!$C$12,C22,"")) | E22: =IF(18<='1. Original Loan Setup'!$C$12,C22*'1. Original Loan Setup'!$C$10/365*(B22-EDATE(B22,-1)),"") | F22: =IF(18<='1. Original Loan Setup'!$C$12,(D22+E22)*'1. Original Loan Setup'!$C$17,"") | G22: =IF(18<='1. Original Loan Setup'!$C$12,D22+E22+F22,"") | H22: =IF(18<='1. Original Loan Setup'!$C$12,C22-D22,"")
A23: =IF(19<='1. Original Loan Setup'!$C$12,19,"") | B23: =IF(19<='1. Original Loan Setup'!$C$12,EDATE('1. Original Loan Setup'!$C$13,19-1),"") | C23: =IF(19<='1. Original Loan Setup'!$C$12,H22,"") | D23: =IF(19<'1. Original Loan Setup'!$C$12,'1. Original Loan Setup'!$C$22-E23,IF(19='1. Original Loan Setup'!$C$12,C23,"")) | E23: =IF(19<='1. Original Loan Setup'!$C$12,C23*'1. Original Loan Setup'!$C$10/365*(B23-EDATE(B23,-1)),"") | F23: =IF(19<='1. Original Loan Setup'!$C$12,(D23+E23)*'1. Original Loan Setup'!$C$17,"") | G23: =IF(19<='1. Original Loan Setup'!$C$12,D23+E23+F23,"") | H23: =IF(19<='1. Original Loan Setup'!$C$12,C23-D23,"")
A24: =IF(20<='1. Original Loan Setup'!$C$12,20,"") | B24: =IF(20<='1. Original Loan Setup'!$C$12,EDATE('1. Original Loan Setup'!$C$13,20-1),"") | C24: =IF(20<='1. Original Loan Setup'!$C$12,H23,"") | D24: =IF(20<'1. Original Loan Setup'!$C$12,'1. Original Loan Setup'!$C$22-E24,IF(20='1. Original Loan Setup'!$C$12,C24,"")) | E24: =IF(20<='1. Original Loan Setup'!$C$12,C24*'1. Original Loan Setup'!$C$10/365*(B24-EDATE(B24,-1)),"") | F24: =IF(20<='1. Original Loan Setup'!$C$12,(D24+E24)*'1. Original Loan Setup'!$C$17,"") | G24: =IF(20<='1. Original Loan Setup'!$C$12,D24+E24+F24,"") | H24: =IF(20<='1. Original Loan Setup'!$C$12,C24-D24,"")
B25: TOTAL | D25: =SUM(D5:D24) -> 20000 | E25: =SUM(E5:E24) -> 11684.774 | F25: =SUM(F5:F24) -> 2886.4829 | G25: =SUM(G5:G24) -> 34571.257

Sheet 3. Restructuring Workup
A1: Restructuring Workup
B2: Type only into the yellow cells (Last Payment Date and DPD). Every other figure below is computed, with its basis stated in column E.
B4: STEP 1 — COLLECTIONS INPUT (from loan monitoring system)
B5: Last Payment Date (last installment date actually paid) | C5: 46083 | E5: Must match an Installment Date on Sheet 2. Leave blank / use the Date Granted if no installment has been paid yet.
B6: As-of / Report Date | C6: 46252
B7: Days Past Due (DPD) — as reported by collections | C7: 138
B9: STEP 2 — OUTSTANDING EXPOSURE AT DEFAULT (computed)
B10: Outstanding Principal (PHP) | C10: =IFERROR(INDEX('2. Original Amort Schedule'!$H$5:$H$24,MATCH(C5,'2. Original Amort Schedule'!$B$5:$B$24,0)),'1. Original Loan Setup'!$C$8) -> 16518.574 | E10: Basis: Ending Balance on Sheet 2 for the row whose Installment Date = Last Payment Date above (i.e., the balance left after the last installment the borrower actually paid).
B11: Accrued Interest during delinquency (PHP) | C11: =C10*'1. Original Loan Setup'!$C$10/365*C7 -> 5933.1098 | E11: Basis: Outstanding Principal x Original Contractual Annual Rate / 365 x DPD (simple daily interest per the original Promissory Note's stated rate). Adjust the rate assumption in Sheet 1 if the bank applies a different penalty-interest rate during delinquency.
B12: Penalty / Late Payment Fees (PHP) | C12: =ROUNDUP(C7/30,0)*'1. Original Loan Setup'!$C$19 -> 2500 | E12: Basis: Late Payment Fee stated on the original Promissory Note x number of missed 30-day installment cycles (ROUNDUP(DPD/30)).
B13: Total Outstanding Exposure (PHP) | C13: =C10+C11+C12 -> 24951.684 | E13: Basis: Outstanding Principal + Accrued Interest + Penalty. This is the borrower's full exposure as of the As-of Date, before any restructuring relief.
B15: STEP 3 — RESTRUCTURING DECISION (per DPD policy; Penalty toggle is manual)
B16: Capitalize Accrued Interest into new Principal? (auto, per DPD policy) | C16: =IF(C7>90,"No","Yes") -> No | E16: Policy rule (not manually editable): if DPD > 90 days, the restructured loan is the Outstanding Principal ONLY (accrued interest is waived). If DPD is 90 days or less, the restructured loan is Outstanding Principal PLUS Accrued Interest (interest is capitalized). Driven automatically by the DPD entered in Step 1.
B17: Capitalize Penalty into new Principal? (manual) | C17: No | E17: Yes/No — manual choice, not covered by the DPD policy above. In the sample restructured PN supplied, penalty was WAIVED (No).
B19: RESTRUCTURED LOAN — NEW TERMS
B20: New Restructured Principal (PHP) | C20: =C10+IF(C16="Yes",C11,0)+IF(C17="Yes",C12,0) -> 16518.574 | E20: Basis: Outstanding Principal, plus Accrued Interest if DPD <= 90 (per policy above), plus Penalty only if manually capitalized.
B21: New Annual Interest Rate (APR) | C21: 0.475
B22: New Monthly Interest Rate | C22: =C21/12 -> 0.039583333
B23: New Number of Installments | C23: 16
B24: New First Monthly Due Date | C24: 46300
B25: New Date Granted (restructuring date) | C25: 46252
B26: New Fixed Monthly Installment (Principal+Interest) | C26: =-PMT(C22,C23,C20) -> 1413.2701
B27: New Maturity Date | C27: =EDATE(C24,C23-1) -> 46757
B28: Total of New Payments over the term (PHP) | C28: =C26*C23 -> 22612.322
B29: Total Waived (Interest + Penalty not capitalized) (PHP) | C29: =IF(C16="No",C11,0)+IF(C17="No",C12,0) -> 8433.1098

Sheet 4. Restructured Amort Sched
A1: Restructured Loan — Amortization Schedule
A2: Auto-generated from Sheet 3 (New Restructured Principal, Rate, Term, First Due Date, Date Granted). Same actual/365 daily-interest mechanics as Sheet 2; no VAS fee on the restructured loan (per the sample restructured Promissory Note supplied).
A4: No. | B4: Installment Date | C4: Beginning Balance | D4: Principal | E4: Interest | F4: Total Payment | G4: Ending Balance
A5: =IF(1<='3. Restructuring Workup'!$C$23,1,"") -> 1 | B5: =IF(1<='3. Restructuring Workup'!$C$23,EDATE('3. Restructuring Workup'!$C$24,1-1),"") -> 46300 | C5: =IF(1<='3. Restructuring Workup'!$C$23,'3. Restructuring Workup'!$C$20,"") -> 16518.574 | D5: =IF(1<'3. Restructuring Workup'!$C$23,'3. Restructuring Workup'!$C$26-E5,IF(1='3. Restructuring Workup'!$C$23,C5,"")) -> 768.36687 | E5: =IF(1<='3. Restructuring Workup'!$C$23,C5*'3. Restructuring Workup'!$C$21/365*(B5-EDATE(B5,-1)),"") -> 644.90324 | F5: =IF(1<='3. Restructuring Workup'!$C$23,D5+E5,"") -> 1413.2701 | G5: =IF(1<='3. Restructuring Workup'!$C$23,C5-D5,"") -> 15750.207
A6: =IF(2<='3. Restructuring Workup'!$C$23,2,"") -> 2 | B6: =IF(2<='3. Restructuring Workup'!$C$23,EDATE('3. Restructuring Workup'!$C$24,2-1),"") -> 46331 | C6: =IF(2<='3. Restructuring Workup'!$C$23,G5,"") -> 15750.207 | D6: =IF(2<'3. Restructuring Workup'!$C$23,'3. Restructuring Workup'!$C$26-E6,IF(2='3. Restructuring Workup'!$C$23,C6,"")) -> 777.86791 | E6: =IF(2<='3. Restructuring Workup'!$C$23,C6*'3. Restructuring Workup'!$C$21/365*(B6-EDATE(B6,-1)),"") -> 635.4022 | F6: =IF(2<='3. Restructuring Workup'!$C$23,D6+E6,"") -> 1413.2701 | G6: =IF(2<='3. Restructuring Workup'!$C$23,C6-D6,"") -> 14972.34
A7: =IF(3<='3. Restructuring Workup'!$C$23,3,"") -> 3 | B7: =IF(3<='3. Restructuring Workup'!$C$23,EDATE('3. Restructuring Workup'!$C$24,3-1),"") -> 46361 | C7: =IF(3<='3. Restructuring Workup'!$C$23,G6,"") -> 14972.34 | D7: =IF(3<'3. Restructuring Workup'!$C$23,'3. Restructuring Workup'!$C$26-E7,IF(3='3. Restructuring Workup'!$C$23,C7,"")) -> 828.73357 | E7: =IF(3<='3. Restructuring Workup'!$C$23,C7*'3. Restructuring Workup'!$C$21/365*(B7-EDATE(B7,-1)),"") -> 584.53654 | F7: =IF(3<='3. Restructuring Workup'!$C$23,D7+E7,"") -> 1413.2701 | G7: =IF(3<='3. Restructuring Workup'!$C$23,C7-D7,"") -> 14143.606
A8: =IF(4<='3. Restructuring Workup'!$C$23,4,"") -> 4 | B8: =IF(4<='3. Restructuring Workup'!$C$23,EDATE('3. Restructuring Workup'!$C$24,4-1),"") -> 46392 | C8: =IF(4<='3. Restructuring Workup'!$C$23,G7,"") -> 14143.606 | D8: =IF(4<'3. Restructuring Workup'!$C$23,'3. Restructuring Workup'!$C$26-E8,IF(4='3. Restructuring Workup'!$C$23,C8,"")) -> 842.68217 | E8: =IF(4<='3. Restructuring Workup'!$C$23,C8*'3. Restructuring Workup'!$C$21/365*(B8-EDATE(B8,-1)),"") -> 570.58794 | F8: =IF(4<='3. Restructuring Workup'!$C$23,D8+E8,"") -> 1413.2701 | G8: =IF(4<='3. Restructuring Workup'!$C$23,C8-D8,"") -> 13300.924
A9: =IF(5<='3. Restructuring Workup'!$C$23,5,"") -> 5 | B9: =IF(5<='3. Restructuring Workup'!$C$23,EDATE('3. Restructuring Workup'!$C$24,5-1),"") -> 46423 | C9: =IF(5<='3. Restructuring Workup'!$C$23,G8,"") -> 13300.924 | D9: =IF(5<'3. Restructuring Workup'!$C$23,'3. Restructuring Workup'!$C$26-E9,IF(5='3. Restructuring Workup'!$C$23,C9,"")) -> 876.67805 | E9: =IF(5<='3. Restructuring Workup'!$C$23,C9*'3. Restructuring Workup'!$C$21/365*(B9-EDATE(B9,-1)),"") -> 536.59206 | F9: =IF(5<='3. Restructuring Workup'!$C$23,D9+E9,"") -> 1413.2701 | G9: =IF(5<='3. Restructuring Workup'!$C$23,C9-D9,"") -> 12424.246
A10: =IF(6<='3. Restructuring Workup'!$C$23,6,"") -> 6 | B10: =IF(6<='3. Restructuring Workup'!$C$23,EDATE('3. Restructuring Workup'!$C$24,6-1),"") -> 46451 | C10: =IF(6<='3. Restructuring Workup'!$C$23,G9,"") -> 12424.246 | D10: =IF(6<'3. Restructuring Workup'!$C$23,'3. Restructuring Workup'!$C$26-E10,IF(6='3. Restructuring Workup'!$C$23,C10,"")) -> 960.55102 | E10: =IF(6<='3. Restructuring Workup'!$C$23,C10*'3. Restructuring Workup'!$C$21/365*(B10-EDATE(B10,-1)),"") -> 452.71909 | F10: =IF(6<='3. Restructuring Workup'!$C$23,D10+E10,"") -> 1413.2701 | G10: =IF(6<='3. Restructuring Workup'!$C$23,C10-D10,"") -> 11463.695
A11: =IF(7<='3. Restructuring Workup'!$C$23,7,"") -> 7 | B11: =IF(7<='3. Restructuring Workup'!$C$23,EDATE('3. Restructuring Workup'!$C$24,7-1),"") -> 46482 | C11: =IF(7<='3. Restructuring Workup'!$C$23,G10,"") -> 11463.695 | D11: =IF(7<'3. Restructuring Workup'!$C$23,'3. Restructuring Workup'!$C$26-E11,IF(7='3. Restructuring Workup'!$C$23,C11,"")) -> 950.7964 | E11: =IF(7<='3. Restructuring Workup'!$C$23,C11*'3. Restructuring Workup'!$C$21/365*(B11-EDATE(B11,-1)),"") -> 462.47371 | F11: =IF(7<='3. Restructuring Workup'!$C$23,D11+E11,"") -> 1413.2701 | G11: =IF(7<='3. Restructuring Workup'!$C$23,C11-D11,"") -> 10512.898
A12: =IF(8<='3. Restructuring Workup'!$C$23,8,"") -> 8 | B12: =IF(8<='3. Restructuring Workup'!$C$23,EDATE('3. Restructuring Workup'!$C$24,8-1),"") -> 46512 | C12: =IF(8<='3. Restructuring Workup'!$C$23,G11,"") -> 10512.898 | D12: =IF(8<'3. Restructuring Workup'!$C$23,'3. Restructuring Workup'!$C$26-E12,IF(8='3. Restructuring Workup'!$C$23,C12,"")) -> 1002.835 | E12: =IF(8<='3. Restructuring Workup'!$C$23,C12*'3. Restructuring Workup'!$C$21/365*(B12-EDATE(B12,-1)),"") -> 410.43507 | F12: =IF(8<='3. Restructuring Workup'!$C$23,D12+E12,"") -> 1413.2701 | G12: =IF(8<='3. Restructuring Workup'!$C$23,C12-D12,"") -> 9510.0633
A13: =IF(9<='3. Restructuring Workup'!$C$23,9,"") -> 9 | B13: =IF(9<='3. Restructuring Workup'!$C$23,EDATE('3. Restructuring Workup'!$C$24,9-1),"") -> 46543 | C13: =IF(9<='3. Restructuring Workup'!$C$23,G12,"") -> 9510.0633 | D13: =IF(9<'3. Restructuring Workup'!$C$23,'3. Restructuring Workup'!$C$26-E13,IF(9='3. Restructuring Workup'!$C$23,C13,"")) -> 1029.6107 | E13: =IF(9<='3. Restructuring Workup'!$C$23,C13*'3. Restructuring Workup'!$C$21/365*(B13-EDATE(B13,-1)),"") -> 383.6594 | F13: =IF(9<='3. Restructuring Workup'!$C$23,D13+E13,"") -> 1413.2701 | G13: =IF(9<='3. Restructuring Workup'!$C$23,C13-D13,"") -> 8480.4526
A14: =IF(10<='3. Restructuring Workup'!$C$23,10,"") -> 10 | B14: =IF(10<='3. Restructuring Workup'!$C$23,EDATE('3. Restructuring Workup'!$C$24,10-1),"") -> 46573 | C14: =IF(10<='3. Restructuring Workup'!$C$23,G13,"") -> 8480.4526 | D14: =IF(10<'3. Restructuring Workup'!$C$23,'3. Restructuring Workup'!$C$26-E14,IF(10='3. Restructuring Workup'!$C$23,C14,"")) -> 1082.184 | E14: =IF(10<='3. Restructuring Workup'!$C$23,C14*'3. Restructuring Workup'!$C$21/365*(B14-EDATE(B14,-1)),"") -> 331.08616 | F14: =IF(10<='3. Restructuring Workup'!$C$23,D14+E14,"") -> 1413.2701 | G14: =IF(10<='3. Restructuring Workup'!$C$23,C14-D14,"") -> 7398.2686
A15: =IF(11<='3. Restructuring Workup'!$C$23,11,"") -> 11 | B15: =IF(11<='3. Restructuring Workup'!$C$23,EDATE('3. Restructuring Workup'!$C$24,11-1),"") -> 46604 | C15: =IF(11<='3. Restructuring Workup'!$C$23,G14,"") -> 7398.2686 | D15: =IF(11<'3. Restructuring Workup'!$C$23,'3. Restructuring Workup'!$C$26-E15,IF(11='3. Restructuring Workup'!$C$23,C15,"")) -> 1114.8057 | E15: =IF(11<='3. Restructuring Workup'!$C$23,C15*'3. Restructuring Workup'!$C$21/365*(B15-EDATE(B15,-1)),"") -> 298.4644 | F15: =IF(11<='3. Restructuring Workup'!$C$23,D15+E15,"") -> 1413.2701 | G15: =IF(11<='3. Restructuring Workup'!$C$23,C15-D15,"") -> 6283.4629
A16: =IF(12<='3. Restructuring Workup'!$C$23,12,"") -> 12 | B16: =IF(12<='3. Restructuring Workup'!$C$23,EDATE('3. Restructuring Workup'!$C$24,12-1),"") -> 46635 | C16: =IF(12<='3. Restructuring Workup'!$C$23,G15,"") -> 6283.4629 | D16: =IF(12<'3. Restructuring Workup'!$C$23,'3. Restructuring Workup'!$C$26-E16,IF(12='3. Restructuring Workup'!$C$23,C16,"")) -> 1159.7797 | E16: =IF(12<='3. Restructuring Workup'!$C$23,C16*'3. Restructuring Workup'!$C$21/365*(B16-EDATE(B16,-1)),"") -> 253.49039 | F16: =IF(12<='3. Restructuring Workup'!$C$23,D16+E16,"") -> 1413.2701 | G16: =IF(12<='3. Restructuring Workup'!$C$23,C16-D16,"") -> 5123.6832
A17: =IF(13<='3. Restructuring Workup'!$C$23,13,"") -> 13 | B17: =IF(13<='3. Restructuring Workup'!$C$23,EDATE('3. Restructuring Workup'!$C$24,13-1),"") -> 46665 | C17: =IF(13<='3. Restructuring Workup'!$C$23,G16,"") -> 5123.6832 | D17: =IF(13<'3. Restructuring Workup'!$C$23,'3. Restructuring Workup'!$C$26-E17,IF(13='3. Restructuring Workup'!$C$23,C17,"")) -> 1213.2359 | E17: =IF(13<='3. Restructuring Workup'!$C$23,C17*'3. Restructuring Workup'!$C$21/365*(B17-EDATE(B17,-1)),"") -> 200.03421 | F17: =IF(13<='3. Restructuring Workup'!$C$23,D17+E17,"") -> 1413.2701 | G17: =IF(13<='3. Restructuring Workup'!$C$23,C17-D17,"") -> 3910.4473
A18: =IF(14<='3. Restructuring Workup'!$C$23,14,"") -> 14 | B18: =IF(14<='3. Restructuring Workup'!$C$23,EDATE('3. Restructuring Workup'!$C$24,14-1),"") -> 46696 | C18: =IF(14<='3. Restructuring Workup'!$C$23,G17,"") -> 3910.4473 | D18: =IF(14<'3. Restructuring Workup'!$C$23,'3. Restructuring Workup'!$C$26-E18,IF(14='3. Restructuring Workup'!$C$23,C18,"")) -> 1255.513 | E18: =IF(14<='3. Restructuring Workup'!$C$23,C18*'3. Restructuring Workup'!$C$21/365*(B18-EDATE(B18,-1)),"") -> 157.75709 | F18: =IF(14<='3. Restructuring Workup'!$C$23,D18+E18,"") -> 1413.2701 | G18: =IF(14<='3. Restructuring Workup'!$C$23,C18-D18,"") -> 2654.9342
A19: =IF(15<='3. Restructuring Workup'!$C$23,15,"") -> 15 | B19: =IF(15<='3. Restructuring Workup'!$C$23,EDATE('3. Restructuring Workup'!$C$24,15-1),"") -> 46726 | C19: =IF(15<='3. Restructuring Workup'!$C$23,G18,"") -> 2654.9342 | D19: =IF(15<'3. Restructuring Workup'!$C$23,'3. Restructuring Workup'!$C$26-E19,IF(15='3. Restructuring Workup'!$C$23,C19,"")) -> 1309.6186 | E19: =IF(15<='3. Restructuring Workup'!$C$23,C19*'3. Restructuring Workup'!$C$21/365*(B19-EDATE(B19,-1)),"") -> 103.65154 | F19: =IF(15<='3. Restructuring Workup'!$C$23,D19+E19,"") -> 1413.2701 | G19: =IF(15<='3. Restructuring Workup'!$C$23,C19-D19,"") -> 1345.3157
A20: =IF(16<='3. Restructuring Workup'!$C$23,16,"") -> 16 | B20: =IF(16<='3. Restructuring Workup'!$C$23,EDATE('3. Restructuring Workup'!$C$24,16-1),"") -> 46757 | C20: =IF(16<='3. Restructuring Workup'!$C$23,G19,"") -> 1345.3157 | D20: =IF(16<'3. Restructuring Workup'!$C$23,'3. Restructuring Workup'!$C$26-E20,IF(16='3. Restructuring Workup'!$C$23,C20,"")) -> 1345.3157 | E20: =IF(16<='3. Restructuring Workup'!$C$23,C20*'3. Restructuring Workup'!$C$21/365*(B20-EDATE(B20,-1)),"") -> 54.273351 | F20: =IF(16<='3. Restructuring Workup'!$C$23,D20+E20,"") -> 1399.589 | G20: =IF(16<='3. Restructuring Workup'!$C$23,C20-D20,"") -> 0
A21: =IF(17<='3. Restructuring Workup'!$C$23,17,"") | B21: =IF(17<='3. Restructuring Workup'!$C$23,EDATE('3. Restructuring Workup'!$C$24,17-1),"") | C21: =IF(17<='3. Restructuring Workup'!$C$23,G20,"") | D21: =IF(17<'3. Restructuring Workup'!$C$23,'3. Restructuring Workup'!$C$26-E21,IF(17='3. Restructuring Workup'!$C$23,C21,"")) | E21: =IF(17<='3. Restructuring Workup'!$C$23,C21*'3. Restructuring Workup'!$C$21/365*(B21-EDATE(B21,-1)),"") | F21: =IF(17<='3. Restructuring Workup'!$C$23,D21+E21,"") | G21: =IF(17<='3. Restructuring Workup'!$C$23,C21-D21,"")
A22: =IF(18<='3. Restructuring Workup'!$C$23,18,"") | B22: =IF(18<='3. Restructuring Workup'!$C$23,EDATE('3. Restructuring Workup'!$C$24,18-1),"") | C22: =IF(18<='3. Restructuring Workup'!$C$23,G21,"") | D22: =IF(18<'3. Restructuring Workup'!$C$23,'3. Restructuring Workup'!$C$26-E22,IF(18='3. Restructuring Workup'!$C$23,C22,"")) | E22: =IF(18<='3. Restructuring Workup'!$C$23,C22*'3. Restructuring Workup'!$C$21/365*(B22-EDATE(B22,-1)),"") | F22: =IF(18<='3. Restructuring Workup'!$C$23,D22+E22,"") | G22: =IF(18<='3. Restructuring Workup'!$C$23,C22-D22,"")
A23: =IF(19<='3. Restructuring Workup'!$C$23,19,"") | B23: =IF(19<='3. Restructuring Workup'!$C$23,EDATE('3. Restructuring Workup'!$C$24,19-1),"") | C23: =IF(19<='3. Restructuring Workup'!$C$23,G22,"") | D23: =IF(19<'3. Restructuring Workup'!$C$23,'3. Restructuring Workup'!$C$26-E23,IF(19='3. Restructuring Workup'!$C$23,C23,"")) | E23: =IF(19<='3. Restructuring Workup'!$C$23,C23*'3. Restructuring Workup'!$C$21/365*(B23-EDATE(B23,-1)),"") | F23: =IF(19<='3. Restructuring Workup'!$C$23,D23+E23,"") | G23: =IF(19<='3. Restructuring Workup'!$C$23,C23-D23,"")
A24: =IF(20<='3. Restructuring Workup'!$C$23,20,"") | B24: =IF(20<='3. Restructuring Workup'!$C$23,EDATE('3. Restructuring Workup'!$C$24,20-1),"") | C24: =IF(20<='3. Restructuring Workup'!$C$23,G23,"") | D24: =IF(20<'3. Restructuring Workup'!$C$23,'3. Restructuring Workup'!$C$26-E24,IF(20='3. Restructuring Workup'!$C$23,C24,"")) | E24: =IF(20<='3. Restructuring Workup'!$C$23,C24*'3. Restructuring Workup'!$C$21/365*(B24-EDATE(B24,-1)),"") | F24: =IF(20<='3. Restructuring Workup'!$C$23,D24+E24,"") | G24: =IF(20<='3. Restructuring Workup'!$C$23,C24-D24,"")
A25: =IF(21<='3. Restructuring Workup'!$C$23,21,"") | B25: =IF(21<='3. Restructuring Workup'!$C$23,EDATE('3. Restructuring Workup'!$C$24,21-1),"") | C25: =IF(21<='3. Restructuring Workup'!$C$23,G24,"") | D25: =IF(21<'3. Restructuring Workup'!$C$23,'3. Restructuring Workup'!$C$26-E25,IF(21='3. Restructuring Workup'!$C$23,C25,"")) | E25: =IF(21<='3. Restructuring Workup'!$C$23,C25*'3. Restructuring Workup'!$C$21/365*(B25-EDATE(B25,-1)),"") | F25: =IF(21<='3. Restructuring Workup'!$C$23,D25+E25,"") | G25: =IF(21<='3. Restructuring Workup'!$C$23,C25-D25,"")
A26: =IF(22<='3. Restructuring Workup'!$C$23,22,"") | B26: =IF(22<='3. Restructuring Workup'!$C$23,EDATE('3. Restructuring Workup'!$C$24,22-1),"") | C26: =IF(22<='3. Restructuring Workup'!$C$23,G25,"") | D26: =IF(22<'3. Restructuring Workup'!$C$23,'3. Restructuring Workup'!$C$26-E26,IF(22='3. Restructuring Workup'!$C$23,C26,"")) | E26: =IF(22<='3. Restructuring Workup'!$C$23,C26*'3. Restructuring Workup'!$C$21/365*(B26-EDATE(B26,-1)),"") | F26: =IF(22<='3. Restructuring Workup'!$C$23,D26+E26,"") | G26: =IF(22<='3. Restructuring Workup'!$C$23,C26-D26,"")
A27: =IF(23<='3. Restructuring Workup'!$C$23,23,"") | B27: =IF(23<='3. Restructuring Workup'!$C$23,EDATE('3. Restructuring Workup'!$C$24,23-1),"") | C27: =IF(23<='3. Restructuring Workup'!$C$23,G26,"") | D27: =IF(23<'3. Restructuring Workup'!$C$23,'3. Restructuring Workup'!$C$26-E27,IF(23='3. Restructuring Workup'!$C$23,C27,"")) | E27: =IF(23<='3. Restructuring Workup'!$C$23,C27*'3. Restructuring Workup'!$C$21/365*(B27-EDATE(B27,-1)),"") | F27: =IF(23<='3. Restructuring Workup'!$C$23,D27+E27,"") | G27: =IF(23<='3. Restructuring Workup'!$C$23,C27-D27,"")
A28: =IF(24<='3. Restructuring Workup'!$C$23,24,"") | B28: =IF(24<='3. Restructuring Workup'!$C$23,EDATE('3. Restructuring Workup'!$C$24,24-1),"") | C28: =IF(24<='3. Restructuring Workup'!$C$23,G27,"") | D28: =IF(24<'3. Restructuring Workup'!$C$23,'3. Restructuring Workup'!$C$26-E28,IF(24='3. Restructuring Workup'!$C$23,C28,"")) | E28: =IF(24<='3. Restructuring Workup'!$C$23,C28*'3. Restructuring Workup'!$C$21/365*(B28-EDATE(B28,-1)),"") | F28: =IF(24<='3. Restructuring Workup'!$C$23,D28+E28,"") | G28: =IF(24<='3. Restructuring Workup'!$C$23,C28-D28,"")
B29: TOTAL | D29: =SUM(D5:D28) -> 16518.574 | E29: =SUM(E5:E28) -> 6080.0664 | F29: =SUM(F5:F28) -> 22598.641

Sheet 5. Summary
A1: Original vs. Restructured Loan — Summary
B2: All cells below are linked from Sheets 1–4. Nothing to type here.
C4: Original Loan | D4: Restructured Loan
B5: Loan Reference / ID | C5: ='1. Original Loan Setup'!C5 -> e.g. LN-000001 | D5: New reference assigned upon restructuring
B6: Principal (PHP) | C6: ='1. Original Loan Setup'!C8 -> 20000 | D6: ='3. Restructuring Workup'!C20 -> 16518.574
B7: Date Granted | C7: ='1. Original Loan Setup'!C9 -> 45991 | D7: ='3. Restructuring Workup'!C25 -> 46252
B8: Annual Interest Rate | C8: ='1. Original Loan Setup'!C10 -> 0.95 | D8: ='3. Restructuring Workup'!C21 -> 0.475
B9: Number of Installments | C9: ='1. Original Loan Setup'!C12 -> 12 | D9: ='3. Restructuring Workup'!C23 -> 16
B10: First Due Date | C10: ='1. Original Loan Setup'!C13 -> 46024 | D10: ='3. Restructuring Workup'!C24 -> 46300
B11: Maturity Date | C11: ='1. Original Loan Setup'!C23 -> 46358 | D11: ='3. Restructuring Workup'!C27 -> 46757
B12: Fixed Monthly Installment (PHP) | C12: ='1. Original Loan Setup'!C22 -> 2642.4529 | D12: ='3. Restructuring Workup'!C26 -> 1413.2701
B14: DEFAULT / RESTRUCTURING BASIS
B15: Last Payment Date | C15: ='3. Restructuring Workup'!C5 -> 46083
B16: As-of / Report Date | C16: ='3. Restructuring Workup'!C6 -> 46252
B17: Days Past Due (DPD) | C17: ='3. Restructuring Workup'!C7 -> 138
B18: Outstanding Principal at Default (PHP) | C18: ='3. Restructuring Workup'!C10 -> 16518.574
B19: Accrued Interest during Delinquency (PHP) | C19: ='3. Restructuring Workup'!C11 -> 5933.1098
B20: Penalty / Late Fees (PHP) | C20: ='3. Restructuring Workup'!C12 -> 2500
B21: Total Outstanding Exposure (PHP) | C21: ='3. Restructuring Workup'!C13 -> 24951.684
B22: Total Waived (not capitalized) (PHP) | C22: ='3. Restructuring Workup'!C29 -> 8433.1098
B23: New Restructured Principal (PHP) | C23: ='3. Restructuring Workup'!C20 -> 16518.574
